EasyTicket/__init__.py
EasyTicket/__main__.py
EasyTicket/all_threads.py
EasyTicket/app.py
EasyTicket/choose_end_station_UI.py
EasyTicket/choose_start_station_UI.py
EasyTicket/choose_start_time_UI.py
EasyTicket/get_ticket_interface.py
EasyTicket/run.py
EasyTicket/analyze_json/__init__.py
EasyTicket/analyze_json/analyze_city_json.py
EasyTicket/analyze_json/analyze_city_station_json.py
EasyTicket/bin/__init__.py
EasyTicket/bin/deal_browser_driver.py
EasyTicket/bin/get_ticket_info.py
EasyTicket/bin/get_train_code_ticket.py
EasyTicket/bin/get_valid_code_UI.py
EasyTicket/bin/select_ticket_buyer_UI.py
EasyTicket/bin/sign_in_UI.py
EasyTicket/bin/train_info_interface.py
EasyTicket/bin/browsers_searcher/__init__.py
EasyTicket/bin/browsers_searcher/linux_browser_search.py
EasyTicket/bin/browsers_searcher/osx_browser_search.py
EasyTicket/bin/browsers_searcher/windows_browser_search.py
EasyTicket/bin/driver/chromedriver
EasyTicket/bin/driver/chromedriver.exe
EasyTicket/bin/driver/geckodriver
EasyTicket/bin/driver/geckodriver.exe
EasyTicket/bin/driver/msedgedriver
EasyTicket/bin/driver/msedgedriver.exe
EasyTicket/ticket_12306_prog_addition/__init__.py
EasyTicket/ticket_12306_prog_addition/cacert.pem
EasyTicket/ticket_12306_prog_addition/city.json
EasyTicket/ticket_12306_prog_addition/cityTrain.json
EasyTicket/ticket_12306_prog_addition/download_photo.ico
easyticket-1.0.0.dist-info/licenses/LICENSE
easyticket-1.0.0.dist-info/METADATA
easyticket-1.0.0.dist-info/WHEEL
easyticket-1.0.0.dist-info/top_level.txt
easyticket-1.0.0.dist-info/RECORD
