Metadata-Version: 2.4
Name: EasyTicket
Version: 1.0.0
Summary: Get ticket on 12306 by web crawler and selenium driveing the system browser
Author-email: F18-Maverick <xu_ruihong2009@163.com>
License-Expression: GPL-3.0-or-later
Project-URL: Homepage, https://github.com/F18-Maverick/EasyTicket
Project-URL: Issues, https://github.com/F18-Maverick/EasyTicket/issues
Classifier: Programming Language :: Python :: 3
Classifier: Operating System :: OS Independent
Requires-Python: >=3.9
License-File: LICENSE
Requires-Dist: selenium>=4.0.0
Dynamic: license-file
